[
    {
        "id": 76,
        "year": {
            "id": 11,
            "year": "2015"
        },
        "minute": 0,
        "hour": 2,
        "name": "02:00"
    },
    {
        "id": 77,
        "year": {
            "id": 11,
            "year": "2015"
        },
        "minute": 30,
        "hour": 2,
        "name": "02:30"
    },
    {
        "id": 78,
        "year": {
            "id": 11,
            "year": "2015"
        },
        "minute": 0,
        "hour": 3,
        "name": "03:00"
    },
    {
        "id": 79,
        "year": {
            "id": 11,
            "year": "2015"
        },
        "minute": 30,
        "hour": 3,
        "name": "03:30"
    },
    {
        "id": 80,
        "year": {
            "id": 11,
            "year": "2015"
        },
        "minute": 0,
        "hour": 4,
        "name": "04:00"
    },
    {
        "id": 81,
        "year": {
            "id": 11,
            "year": "2015"
        },
        "minute": 30,
        "hour": 4,
        "name": "04:30"
    },
    {
        "id": 82,
        "year": {
            "id": 11,
            "year": "2015"
        },
        "minute": 0,
        "hour": 5,
        "name": "05:00"
    },
    {
        "id": 86,
        "year": {
            "id": 11,
            "year": "2015"
        },
        "minute": 30,
        "hour": 5,
        "name": "05:30"
    },
    {
        "id": 83,
        "year": {
            "id": 11,
            "year": "2015"
        },
        "minute": 0,
        "hour": 6,
        "name": "06:00"
    },
    {
        "id": 84,
        "year": {
            "id": 11,
            "year": "2015"
        },
        "minute": 30,
        "hour": 6,
        "name": "06:30"
    },
    {
        "id": 85,
        "year": {
            "id": 11,
            "year": "2015"
        },
        "minute": 0,
        "hour": 7,
        "name": "07:00"
    },
    {
        "id": 87,
        "year": {
            "id": 11,
            "year": "2015"
        },
        "minute": 30,
        "hour": 7,
        "name": "07:30"
    },
    {
        "id": 88,
        "year": {
            "id": 11,
            "year": "2015"
        },
        "minute": 0,
        "hour": 8,
        "name": "08:00"
    },
    {
        "id": 89,
        "year": {
            "id": 11,
            "year": "2015"
        },
        "minute": 30,
        "hour": 8,
        "name": "08:30"
    },
    {
        "id": 90,
        "year": {
            "id": 11,
            "year": "2015"
        },
        "minute": 0,
        "hour": 9,
        "name": "09:00"
    },
    {
        "id": 91,
        "year": {
            "id": 11,
            "year": "2015"
        },
        "minute": 30,
        "hour": 9,
        "name": "09:30"
    },
    {
        "id": 92,
        "year": {
            "id": 11,
            "year": "2015"
        },
        "minute": 0,
        "hour": 10,
        "name": "10:00"
    }
]